grooper/__init__.py
grooper/core/__init__.py
grooper/core/grooper.py
grooper/exceptions/__init__.py
grooper/exceptions/errors.py
grooper/utils/__init__.py
grooper/utils/tools.py
grooper-0.1.1.dist-info/WHEEL
grooper-0.1.1.dist-info/METADATA
grooper-0.1.1.dist-info/RECORD
