Metadata-Version: 2.1
Name: grooper
Version: 0.1.1
Summary: 
Author: Adrian Carreno
Author-email: adrian.carreno@gomoder.com
Requires-Python: >=3.8,<4.0
Classifier: Programming Language :: Python :: 3
Classifier: Programming Language :: Python :: 3.8
Classifier: Programming Language :: Python :: 3.9
Classifier: Programming Language :: Python :: 3.10
Classifier: Programming Language :: Python :: 3.11
Requires-Dist: requests (>=2.31.0,<3.0.0)
